gitlabx/__init__.py
gitlabx/abstract.py
gitlabx/branches.py
gitlabx/commits.py
gitlabx/deployments.py
gitlabx/events.py
gitlabx/factories.py
gitlabx/issues.py
gitlabx/jobs.py
gitlabx/member.py
gitlabx/merge_request.py
gitlabx/pipelines.py
gitlabx/pipelines_schedules.py
gitlabx/project.py
gitlabx/projectLanguages.py
gitlabx/repositories.py
gitlabx/repositoryTree.py
gitlabx/trriggers.py
gitlabx-0.14.0.dist-info/METADATA
gitlabx-0.14.0.dist-info/WHEEL
gitlabx-0.14.0.dist-info/top_level.txt
gitlabx-0.14.0.dist-info/RECORD
