Metadata-Version: 2.1
Name: gitlabx
Version: 0.14.0
Summary: Uma Lib para buscar dados do Gitlab
Home-page: https://gitlab.com/immigrant-data-driven-development/libs/application/gitlab
Author: Carlos Henrique Maulaz de Freitas
Author-email: carlosmaulaz@gmail.com
Classifier: Programming Language :: Python :: 3
Classifier: License :: OSI Approved :: MIT License
Classifier: Operating System :: OS Independent
Requires-Dist: python-gitlab
Requires-Dist: factory-boy
